torch_pgn/__init__.py
torch_pgn/args.py
torch_pgn/load_data.py
torch_pgn/data/FingerprintDataset.py
torch_pgn/data/ProximityGraphDataset.py
torch_pgn/data/__init__.py
torch_pgn/data/data_utils.py
torch_pgn/data/dmpnn_utils.py
torch_pgn/data/load_data.py
torch_pgn/datasets/FPDataset.py
torch_pgn/datasets/ManyVsManyDataset.py
torch_pgn/datasets/OneVsManyDataset.py
torch_pgn/datasets/PGDataset.py
torch_pgn/datasets/__init__.py
torch_pgn/evaluate/__init__.py
torch_pgn/evaluate/plot_utils.py
torch_pgn/featurization/__init__.py
torch_pgn/featurization/featurize.py
torch_pgn/featurization/simple_featurization.py
torch_pgn/graphs/__init__.py
torch_pgn/graphs/graph_utils.py
torch_pgn/graphs/proximal_residues.py
torch_pgn/graphs/proximity_graph.py
torch_pgn/models/DimeNet.py
torch_pgn/models/FPEncoder.py
torch_pgn/models/GGNet.py
torch_pgn/models/__init__.py
torch_pgn/models/dimenet_utils.py
torch_pgn/models/dmpnn_encoder.py
torch_pgn/models/model.py
torch_pgn/models/nn_utils.py
torch_pgn/models/pfp_encoder.py
torch_pgn/train/Trainer.py
torch_pgn/train/__init__.py
torch_pgn/train/cross_validate_model.py
torch_pgn/train/evaluate_model.py
torch_pgn/train/hyperopt.py
torch_pgn/train/run_training.py
torch_pgn/train/train.py
torch_pgn/train/train_model.py
torch_pgn/train/train_utils.py
torch_pgn-0.1.3.dist-info/LICENSE
torch_pgn-0.1.3.dist-info/METADATA
torch_pgn-0.1.3.dist-info/WHEEL
torch_pgn-0.1.3.dist-info/top_level.txt
torch_pgn-0.1.3.dist-info/RECORD
