Metadata-Version: 2.1
Name: torch-pgn
Version: 0.1.3
Summary: Proximity Graph Networks: Predicting ligand affinity with Message Passing Neural Networks
Home-page: https://github.com/keiserlab/torch_pgn
Author: Keiser Lab
Author-email: keiser@keiserlab.org
License: MIT
Keywords: chemistry,machine learning,affinity prediction,message passing neural network,graph neural network
Classifier: Programming Language :: Python :: 3.7
Classifier: License :: OSI Approved :: MIT License
Classifier: Operating System :: OS Independent
Requires-Python: >3.6,<3.8
License-File: LICENSE
Requires-Dist: torch (>=1.7.0)
Requires-Dist: torch-geometric (>=1.6.3)
Requires-Dist: networkx (>=2.5)
Requires-Dist: typed-argument-parser (==1.6.1)
Requires-Dist: pandas (==1.1.5)
Requires-Dist: rdkit (>=2020.09.3)
Requires-Dist: numpy (<=1.21.6,>=1.19.2)
Requires-Dist: tqdm (>=4.54.1)
Requires-Dist: tensorboard (>2.0)
Requires-Dist: scipy (<1.7)
Requires-Dist: scikit-learn (>=0.23.2)
Requires-Dist: hyperopt (>=0.2.5)
Requires-Dist: sympy (>=1.10.1)
Requires-Dist: optuna (>=3.6.1)
Requires-Dist: matplotlib (>=3.0.0)
Requires-Dist: six (>=1.0.0)
Requires-Dist: oddt (==0.7)
